setup.py
src/digimat/__init__.py
src/digimat.logserver.egg-info/PKG-INFO
src/digimat.logserver.egg-info/SOURCES.txt
src/digimat.logserver.egg-info/dependency_links.txt
src/digimat.logserver.egg-info/namespace_packages.txt
src/digimat.logserver.egg-info/not-zip-safe
src/digimat.logserver.egg-info/requires.txt
src/digimat.logserver.egg-info/top_level.txt
src/digimat/logserver/__init__.py
src/digimat/logserver/__main__.py
src/digimat/logserver/client.py
src/digimat/logserver/colorer.py
src/digimat/logserver/logserver.py