Metadata-Version: 1.1
Name: digimat.logserver
Version: 0.1.3
Summary: Digimat TCP Python Logging Server
Home-page: http://www.digimat.ch
Author: Frederic Hess
Author-email: fhess@st-sa.ch
License: PSF
Platform: UNKNOWN
Classifier: Development Status :: 4 - Beta
Classifier: Programming Language :: Python :: 3
